LICENSE
MANIFEST.in
README.asciidoc
pytest.ini
qutebrowser.py
requirements.txt
setup.py
doc/changelog.asciidoc
doc/qutebrowser.1
doc/qutebrowser.1.asciidoc
doc/img/cheatsheet-big.png
doc/img/cheatsheet-small.png
doc/img/completion.png
doc/img/downloads.png
doc/img/hints.png
doc/img/main.png
doc/img/sponsors/hsr.png
doc/img/sponsors/macstadium.png
misc/Makefile
misc/cheatsheet.svg
misc/org.qutebrowser.qutebrowser.appdata.xml
misc/org.qutebrowser.qutebrowser.desktop
misc/apparmor/usr.bin.qutebrowser
misc/requirements/README.md
misc/requirements/requirements-check-manifest.txt
misc/requirements/requirements-check-manifest.txt-raw
misc/requirements/requirements-dev.txt
misc/requirements/requirements-dev.txt-raw
misc/requirements/requirements-docs.txt
misc/requirements/requirements-docs.txt-raw
misc/requirements/requirements-flake8.txt
misc/requirements/requirements-flake8.txt-raw
misc/requirements/requirements-mypy.txt
misc/requirements/requirements-mypy.txt-raw
misc/requirements/requirements-pyinstaller.txt
misc/requirements/requirements-pyinstaller.txt-raw
misc/requirements/requirements-pylint.txt
misc/requirements/requirements-pylint.txt-raw
misc/requirements/requirements-pyqt-5.15.2.txt
misc/requirements/requirements-pyqt-5.15.2.txt-raw
misc/requirements/requirements-pyqt-5.15.txt
misc/requirements/requirements-pyqt-5.15.txt-raw
misc/requirements/requirements-pyqt-5.txt
misc/requirements/requirements-pyqt-5.txt-raw
misc/requirements/requirements-pyqt-6.2.txt
misc/requirements/requirements-pyqt-6.2.txt-raw
misc/requirements/requirements-pyqt-6.3.txt
misc/requirements/requirements-pyqt-6.3.txt-raw
misc/requirements/requirements-pyqt-6.4.txt
misc/requirements/requirements-pyqt-6.4.txt-raw
misc/requirements/requirements-pyqt-6.5.txt
misc/requirements/requirements-pyqt-6.5.txt-raw
misc/requirements/requirements-pyqt-6.txt
misc/requirements/requirements-pyqt-6.txt-raw
misc/requirements/requirements-pyqt.txt
misc/requirements/requirements-pyqt.txt-raw
qutebrowser.egg-info/PKG-INFO
qutebrowser.egg-info/SOURCES.txt
qutebrowser.egg-info/dependency_links.txt
qutebrowser.egg-info/entry_points.txt
qutebrowser.egg-info/requires.txt
qutebrowser.egg-info/top_level.txt
qutebrowser.egg-info/zip-safe
