Metadata-Version: 2.1
Name: qutebrowser
Version: 3.0.2
Summary: A keyboard-driven, vim-like browser based on Python and Qt.
Home-page: https://www.qutebrowser.org/
Author: Florian Bruhin
Author-email: mail@qutebrowser.org
License: GPL
Keywords: pyqt browser web qt webkit qtwebkit qtwebengine
Classifier: Development Status :: 5 - Production/Stable
Classifier: Environment :: X11 Applications :: Qt
Classifier: Intended Audience :: End Users/Desktop
Classifier: License :: OSI Approved :: GNU General Public License v3 or later (GPLv3+)
Classifier: Natural Language :: English
Classifier: Operating System :: Microsoft :: Windows
Classifier: Operating System :: POSIX :: Linux
Classifier: Operating System :: MacOS
Classifier: Operating System :: POSIX :: BSD
Classifier: Programming Language :: Python :: 3
Classifier: Programming Language :: Python :: 3.8
Classifier: Programming Language :: Python :: 3.9
Classifier: Programming Language :: Python :: 3.10
Classifier: Programming Language :: Python :: 3.11
Classifier: Topic :: Internet
Classifier: Topic :: Internet :: WWW/HTTP
Classifier: Topic :: Internet :: WWW/HTTP :: Browsers
Requires-Python: >=3.8
License-File: LICENSE
Requires-Dist: jinja2
Requires-Dist: PyYAML
Requires-Dist: importlib_resources>=1.1.0; python_version < "3.9"
